<?xml version="1.0" encoding="utf-8"?>
<TextureAtlas imagePath="GF_NEW_YORK.png">
	<!-- Created with Adobe Animate version 22.0.3.179 -->
	<!-- http://www.adobe.com/products/animate.html -->
	<SubTexture name="bop0000" x="10" y="10" width="490" height="678" frameX="-3" frameY="-8" frameWidth="498" frameHeight="688"/>
	<SubTexture name="bop0001" x="510" y="10" width="497" height="680" frameX="0" frameY="-8" frameWidth="498" frameHeight="688"/>
	<SubTexture name="bop0002" x="1017" y="10" width="497" height="679" frameX="0" frameY="-9" frameWidth="498" frameHeight="688"/>
	<SubTexture name="bop0003" x="1524" y="10" width="492" height="678" frameX="-2" frameY="-9" frameWidth="498" frameHeight="688"/>
	<SubTexture name="bop0004" x="2026" y="10" width="490" height="680" frameX="-3" frameY="-6" frameWidth="498" frameHeight="688"/>
	<SubTexture name="bop0005" x="2026" y="10" width="490" height="680" frameX="-3" frameY="-6" frameWidth="498" frameHeight="688"/>
	<SubTexture name="bop0006" x="2526" y="10" width="490" height="684" frameX="-3" frameY="-2" frameWidth="498" frameHeight="688"/>
	<SubTexture name="bop0007" x="3026" y="10" width="490" height="685" frameX="-3" frameY="-1" frameWidth="498" frameHeight="688"/>
	<SubTexture name="bop0008" x="3526" y="10" width="490" height="685" frameX="-3" frameY="-1" frameWidth="498" frameHeight="688"/>
	<SubTexture name="bop0009" x="3526" y="10" width="490" height="685" frameX="-3" frameY="-1" frameWidth="498" frameHeight="688"/>
	<SubTexture name="bop0010" x="4026" y="10" width="490" height="685" frameX="-3" frameY="-1" frameWidth="498" frameHeight="688"/>
	<SubTexture name="bop0011" x="4026" y="10" width="490" height="685" frameX="-3" frameY="-1" frameWidth="498" frameHeight="688"/>
	<SubTexture name="bop0012" x="4026" y="10" width="490" height="685" frameX="-3" frameY="-1" frameWidth="498" frameHeight="688"/>
	<SubTexture name="bop0013" x="4526" y="10" width="490" height="686" frameX="-3" frameY="0" frameWidth="498" frameHeight="688"/>
	<SubTexture name="bop0014" x="4526" y="10" width="490" height="686" frameX="-3" frameY="0" frameWidth="498" frameHeight="688"/>
	<SubTexture name="bop0015" x="5026" y="10" width="490" height="686" frameX="-3" frameY="0" frameWidth="498" frameHeight="688"/>
	<SubTexture name="bop0016" x="5526" y="10" width="497" height="688" frameX="0" frameY="0" frameWidth="498" frameHeight="688"/>
	<SubTexture name="bop0017" x="6033" y="10" width="497" height="684" frameX="0" frameY="-4" frameWidth="498" frameHeight="688"/>
	<SubTexture name="bop0018" x="6540" y="10" width="492" height="683" frameX="-2" frameY="-4" frameWidth="498" frameHeight="688"/>
	<SubTexture name="bop0019" x="7042" y="10" width="490" height="680" frameX="-3" frameY="-6" frameWidth="498" frameHeight="688"/>
	<SubTexture name="bop0020" x="7542" y="10" width="490" height="680" frameX="-3" frameY="-6" frameWidth="498" frameHeight="688"/>
	<SubTexture name="bop0021" x="10" y="708" width="490" height="681" frameX="-3" frameY="-5" frameWidth="498" frameHeight="688"/>
	<SubTexture name="bop0022" x="510" y="708" width="490" height="683" frameX="-3" frameY="-3" frameWidth="498" frameHeight="688"/>
	<SubTexture name="bop0023" x="1010" y="708" width="490" height="683" frameX="-3" frameY="-3" frameWidth="498" frameHeight="688"/>
	<SubTexture name="bop0024" x="1510" y="708" width="490" height="683" frameX="-3" frameY="-3" frameWidth="498" frameHeight="688"/>
	<SubTexture name="bop0025" x="2010" y="708" width="490" height="683" frameX="-3" frameY="-3" frameWidth="498" frameHeight="688"/>
	<SubTexture name="bop0026" x="2010" y="708" width="490" height="683" frameX="-3" frameY="-3" frameWidth="498" frameHeight="688"/>
	<SubTexture name="bop0027" x="2010" y="708" width="490" height="683" frameX="-3" frameY="-3" frameWidth="498" frameHeight="688"/>
	<SubTexture name="bop0028" x="2510" y="708" width="495" height="683" frameX="-3" frameY="-3" frameWidth="498" frameHeight="688"/>
	<SubTexture name="bop0029" x="2510" y="708" width="495" height="683" frameX="-3" frameY="-3" frameWidth="498" frameHeight="688"/>
	<SubTexture name="down0000" x="3015" y="708" width="490" height="665" frameX="-3" frameY="-6" frameWidth="497" frameHeight="674"/>
	<SubTexture name="down0001" x="3515" y="708" width="497" height="668" frameX="0" frameY="-6" frameWidth="497" frameHeight="674"/>
	<SubTexture name="down0002" x="4022" y="708" width="497" height="674"/>
	<SubTexture name="down0003" x="4529" y="708" width="492" height="672" frameX="-2" frameY="0" frameWidth="497" frameHeight="674"/>
	<SubTexture name="down0004" x="5031" y="708" width="490" height="671" frameX="-3" frameY="0" frameWidth="497" frameHeight="674"/>
	<SubTexture name="down0005" x="5031" y="708" width="490" height="671" frameX="-3" frameY="0" frameWidth="497" frameHeight="674"/>
	<SubTexture name="down0006" x="5531" y="708" width="490" height="671" frameX="-3" frameY="0" frameWidth="497" frameHeight="674"/>
	<SubTexture name="down0007" x="5531" y="708" width="490" height="671" frameX="-3" frameY="0" frameWidth="497" frameHeight="674"/>
	<SubTexture name="down0008" x="5531" y="708" width="490" height="671" frameX="-3" frameY="0" frameWidth="497" frameHeight="674"/>
	<SubTexture name="down0009" x="5531" y="708" width="490" height="671" frameX="-3" frameY="0" frameWidth="497" frameHeight="674"/>
	<SubTexture name="down0010" x="5531" y="708" width="490" height="671" frameX="-3" frameY="0" frameWidth="497" frameHeight="674"/>
	<SubTexture name="down0011" x="5531" y="708" width="490" height="671" frameX="-3" frameY="0" frameWidth="497" frameHeight="674"/>
	<SubTexture name="down0012" x="5531" y="708" width="490" height="671" frameX="-3" frameY="0" frameWidth="497" frameHeight="674"/>
	<SubTexture name="down0013" x="5531" y="708" width="490" height="671" frameX="-3" frameY="0" frameWidth="497" frameHeight="674"/>
	<SubTexture name="down0014" x="5531" y="708" width="490" height="671" frameX="-3" frameY="0" frameWidth="497" frameHeight="674"/>
	<SubTexture name="fileNailFull0000" x="6031" y="708" width="498" height="683" frameX="-3" frameY="-8" frameWidth="509" frameHeight="693"/>
	<SubTexture name="fileNailFull0001" x="6031" y="708" width="498" height="683" frameX="-3" frameY="-8" frameWidth="509" frameHeight="693"/>
	<SubTexture name="fileNailFull0002" x="6539" y="708" width="498" height="684" frameX="-3" frameY="-7" frameWidth="509" frameHeight="693"/>
	<SubTexture name="fileNailFull0003" x="6539" y="708" width="498" height="684" frameX="-3" frameY="-7" frameWidth="509" frameHeight="693"/>
	<SubTexture name="fileNailFull0004" x="7047" y="708" width="495" height="685" frameX="-3" frameY="-6" frameWidth="509" frameHeight="693"/>
	<SubTexture name="fileNailFull0005" x="7047" y="708" width="495" height="685" frameX="-3" frameY="-6" frameWidth="509" frameHeight="693"/>
	<SubTexture name="fileNailFull0006" x="7552" y="708" width="494" height="685" frameX="-3" frameY="-6" frameWidth="509" frameHeight="693"/>
	<SubTexture name="fileNailFull0007" x="7552" y="708" width="494" height="685" frameX="-3" frameY="-6" frameWidth="509" frameHeight="693"/>
	<SubTexture name="fileNailFull0008" x="10" y="1403" width="494" height="685" frameX="-3" frameY="-6" frameWidth="509" frameHeight="693"/>
	<SubTexture name="fileNailFull0009" x="10" y="1403" width="494" height="685" frameX="-3" frameY="-6" frameWidth="509" frameHeight="693"/>
	<SubTexture name="fileNailFull0010" x="514" y="1403" width="496" height="685" frameX="-3" frameY="-6" frameWidth="509" frameHeight="693"/>
	<SubTexture name="fileNailFull0011" x="514" y="1403" width="496" height="685" frameX="-3" frameY="-6" frameWidth="509" frameHeight="693"/>
	<SubTexture name="fileNailFull0012" x="1020" y="1403" width="498" height="684" frameX="-3" frameY="-7" frameWidth="509" frameHeight="693"/>
	<SubTexture name="fileNailFull0013" x="1020" y="1403" width="498" height="684" frameX="-3" frameY="-7" frameWidth="509" frameHeight="693"/>
	<SubTexture name="fileNailFull0014" x="6031" y="708" width="498" height="683" frameX="-3" frameY="-8" frameWidth="509" frameHeight="693"/>
	<SubTexture name="fileNailFull0015" x="6031" y="708" width="498" height="683" frameX="-3" frameY="-8" frameWidth="509" frameHeight="693"/>
	<SubTexture name="fileNailFull0016" x="6539" y="708" width="498" height="684" frameX="-3" frameY="-7" frameWidth="509" frameHeight="693"/>
	<SubTexture name="fileNailFull0017" x="6539" y="708" width="498" height="684" frameX="-3" frameY="-7" frameWidth="509" frameHeight="693"/>
	<SubTexture name="fileNailFull0018" x="7047" y="708" width="495" height="685" frameX="-3" frameY="-6" frameWidth="509" frameHeight="693"/>
	<SubTexture name="fileNailFull0019" x="7047" y="708" width="495" height="685" frameX="-3" frameY="-6" frameWidth="509" frameHeight="693"/>
	<SubTexture name="fileNailFull0020" x="7552" y="708" width="494" height="685" frameX="-3" frameY="-6" frameWidth="509" frameHeight="693"/>
	<SubTexture name="fileNailFull0021" x="7552" y="708" width="494" height="685" frameX="-3" frameY="-6" frameWidth="509" frameHeight="693"/>
	<SubTexture name="fileNailFull0022" x="10" y="1403" width="494" height="685" frameX="-3" frameY="-6" frameWidth="509" frameHeight="693"/>
	<SubTexture name="fileNailFull0023" x="10" y="1403" width="494" height="685" frameX="-3" frameY="-6" frameWidth="509" frameHeight="693"/>
	<SubTexture name="fileNailFull0024" x="514" y="1403" width="496" height="685" frameX="-3" frameY="-6" frameWidth="509" frameHeight="693"/>
	<SubTexture name="fileNailFull0025" x="514" y="1403" width="496" height="685" frameX="-3" frameY="-6" frameWidth="509" frameHeight="693"/>
	<SubTexture name="fileNailFull0026" x="1020" y="1403" width="498" height="684" frameX="-3" frameY="-7" frameWidth="509" frameHeight="693"/>
	<SubTexture name="fileNailFull0027" x="1020" y="1403" width="498" height="684" frameX="-3" frameY="-7" frameWidth="509" frameHeight="693"/>
	<SubTexture name="fileNailFull0028" x="6031" y="708" width="498" height="683" frameX="-3" frameY="-8" frameWidth="509" frameHeight="693"/>
	<SubTexture name="fileNailFull0029" x="6031" y="708" width="498" height="683" frameX="-3" frameY="-8" frameWidth="509" frameHeight="693"/>
	<SubTexture name="fileNailFull0030" x="6539" y="708" width="498" height="684" frameX="-3" frameY="-7" frameWidth="509" frameHeight="693"/>
	<SubTexture name="fileNailFull0031" x="6539" y="708" width="498" height="684" frameX="-3" frameY="-7" frameWidth="509" frameHeight="693"/>
	<SubTexture name="fileNailFull0032" x="7047" y="708" width="495" height="685" frameX="-3" frameY="-6" frameWidth="509" frameHeight="693"/>
	<SubTexture name="fileNailFull0033" x="7047" y="708" width="495" height="685" frameX="-3" frameY="-6" frameWidth="509" frameHeight="693"/>
	<SubTexture name="fileNailFull0034" x="7552" y="708" width="494" height="685" frameX="-3" frameY="-6" frameWidth="509" frameHeight="693"/>
	<SubTexture name="fileNailFull0035" x="7552" y="708" width="494" height="685" frameX="-3" frameY="-6" frameWidth="509" frameHeight="693"/>
	<SubTexture name="fileNailFull0036" x="10" y="1403" width="494" height="685" frameX="-3" frameY="-6" frameWidth="509" frameHeight="693"/>
	<SubTexture name="fileNailFull0037" x="10" y="1403" width="494" height="685" frameX="-3" frameY="-6" frameWidth="509" frameHeight="693"/>
	<SubTexture name="fileNailFull0038" x="514" y="1403" width="496" height="685" frameX="-3" frameY="-6" frameWidth="509" frameHeight="693"/>
	<SubTexture name="fileNailFull0039" x="514" y="1403" width="496" height="685" frameX="-3" frameY="-6" frameWidth="509" frameHeight="693"/>
	<SubTexture name="fileNailFull0040" x="1020" y="1403" width="498" height="684" frameX="-3" frameY="-7" frameWidth="509" frameHeight="693"/>
	<SubTexture name="fileNailFull0041" x="1020" y="1403" width="498" height="684" frameX="-3" frameY="-7" frameWidth="509" frameHeight="693"/>
	<SubTexture name="fileNailFull0042" x="6031" y="708" width="498" height="683" frameX="-3" frameY="-8" frameWidth="509" frameHeight="693"/>
	<SubTexture name="fileNailFull0043" x="6031" y="708" width="498" height="683" frameX="-3" frameY="-8" frameWidth="509" frameHeight="693"/>
	<SubTexture name="fileNailFull0044" x="6539" y="708" width="498" height="684" frameX="-3" frameY="-7" frameWidth="509" frameHeight="693"/>
	<SubTexture name="fileNailFull0045" x="6539" y="708" width="498" height="684" frameX="-3" frameY="-7" frameWidth="509" frameHeight="693"/>
	<SubTexture name="fileNailFull0046" x="7047" y="708" width="495" height="685" frameX="-3" frameY="-6" frameWidth="509" frameHeight="693"/>
	<SubTexture name="fileNailFull0047" x="7047" y="708" width="495" height="685" frameX="-3" frameY="-6" frameWidth="509" frameHeight="693"/>
	<SubTexture name="fileNailFull0048" x="7552" y="708" width="494" height="685" frameX="-3" frameY="-6" frameWidth="509" frameHeight="693"/>
	<SubTexture name="fileNailFull0049" x="7552" y="708" width="494" height="685" frameX="-3" frameY="-6" frameWidth="509" frameHeight="693"/>
	<SubTexture name="fileNailFull0050" x="10" y="1403" width="494" height="685" frameX="-3" frameY="-6" frameWidth="509" frameHeight="693"/>
	<SubTexture name="fileNailFull0051" x="10" y="1403" width="494" height="685" frameX="-3" frameY="-6" frameWidth="509" frameHeight="693"/>
	<SubTexture name="fileNailFull0052" x="514" y="1403" width="496" height="685" frameX="-3" frameY="-6" frameWidth="509" frameHeight="693"/>
	<SubTexture name="fileNailFull0053" x="514" y="1403" width="496" height="685" frameX="-3" frameY="-6" frameWidth="509" frameHeight="693"/>
	<SubTexture name="fileNailFull0054" x="1020" y="1403" width="498" height="684" frameX="-3" frameY="-7" frameWidth="509" frameHeight="693"/>
	<SubTexture name="fileNailFull0055" x="1528" y="1403" width="498" height="683" frameX="-3" frameY="-8" frameWidth="509" frameHeight="693"/>
	<SubTexture name="fileNailFull0056" x="1528" y="1403" width="498" height="683" frameX="-3" frameY="-8" frameWidth="509" frameHeight="693"/>
	<SubTexture name="fileNailFull0057" x="2036" y="1403" width="498" height="684" frameX="-3" frameY="-7" frameWidth="509" frameHeight="693"/>
	<SubTexture name="fileNailFull0058" x="2036" y="1403" width="498" height="684" frameX="-3" frameY="-7" frameWidth="509" frameHeight="693"/>
	<SubTexture name="fileNailFull0059" x="2544" y="1403" width="495" height="685" frameX="-3" frameY="-6" frameWidth="509" frameHeight="693"/>
	<SubTexture name="fileNailFull0060" x="2544" y="1403" width="495" height="685" frameX="-3" frameY="-6" frameWidth="509" frameHeight="693"/>
	<SubTexture name="fileNailFull0061" x="3049" y="1403" width="494" height="685" frameX="-3" frameY="-6" frameWidth="509" frameHeight="693"/>
	<SubTexture name="fileNailFull0062" x="3049" y="1403" width="494" height="685" frameX="-3" frameY="-6" frameWidth="509" frameHeight="693"/>
	<SubTexture name="fileNailFull0063" x="3553" y="1403" width="494" height="685" frameX="-3" frameY="-6" frameWidth="509" frameHeight="693"/>
	<SubTexture name="fileNailFull0064" x="3553" y="1403" width="494" height="685" frameX="-3" frameY="-6" frameWidth="509" frameHeight="693"/>
	<SubTexture name="fileNailFull0065" x="4057" y="1403" width="496" height="685" frameX="-3" frameY="-6" frameWidth="509" frameHeight="693"/>
	<SubTexture name="fileNailFull0066" x="4057" y="1403" width="496" height="685" frameX="-3" frameY="-6" frameWidth="509" frameHeight="693"/>
	<SubTexture name="fileNailFull0067" x="4563" y="1403" width="498" height="684" frameX="-3" frameY="-7" frameWidth="509" frameHeight="693"/>
	<SubTexture name="fileNailFull0068" x="4563" y="1403" width="498" height="684" frameX="-3" frameY="-7" frameWidth="509" frameHeight="693"/>
	<SubTexture name="fileNailFull0069" x="5071" y="1403" width="502" height="680" frameX="-3" frameY="-11" frameWidth="509" frameHeight="693"/>
	<SubTexture name="fileNailFull0070" x="5071" y="1403" width="502" height="680" frameX="-3" frameY="-11" frameWidth="509" frameHeight="693"/>
	<SubTexture name="fileNailFull0071" x="5583" y="1403" width="506" height="683" frameX="-3" frameY="-8" frameWidth="509" frameHeight="693"/>
	<SubTexture name="fileNailFull0072" x="5583" y="1403" width="506" height="683" frameX="-3" frameY="-8" frameWidth="509" frameHeight="693"/>
	<SubTexture name="fileNailFull0073" x="6099" y="1403" width="494" height="691" frameX="-3" frameY="0" frameWidth="509" frameHeight="693"/>
	<SubTexture name="fileNailFull0074" x="6099" y="1403" width="494" height="691" frameX="-3" frameY="0" frameWidth="509" frameHeight="693"/>
	<SubTexture name="fileNailFull0075" x="6603" y="1403" width="493" height="688" frameX="-3" frameY="-3" frameWidth="509" frameHeight="693"/>
	<SubTexture name="fileNailFull0076" x="6603" y="1403" width="493" height="688" frameX="-3" frameY="-3" frameWidth="509" frameHeight="693"/>
	<SubTexture name="fileNailFull0077" x="7106" y="1403" width="498" height="684" frameX="-3" frameY="-7" frameWidth="509" frameHeight="693"/>
	<SubTexture name="fileNailFull0078" x="7106" y="1403" width="498" height="684" frameX="-3" frameY="-7" frameWidth="509" frameHeight="693"/>
	<SubTexture name="fileNailFull0079" x="7614" y="1403" width="498" height="684" frameX="-3" frameY="-7" frameWidth="509" frameHeight="693"/>
	<SubTexture name="fileNailFull0080" x="7614" y="1403" width="498" height="684" frameX="-3" frameY="-7" frameWidth="509" frameHeight="693"/>
	<SubTexture name="fileNailFull0081" x="10" y="2104" width="498" height="684" frameX="-3" frameY="-7" frameWidth="509" frameHeight="693"/>
	<SubTexture name="fileNailFull0082" x="10" y="2104" width="498" height="684" frameX="-3" frameY="-7" frameWidth="509" frameHeight="693"/>
	<SubTexture name="fileNailFull0083" x="518" y="2104" width="498" height="684" frameX="-3" frameY="-7" frameWidth="509" frameHeight="693"/>
	<SubTexture name="fileNailFull0084" x="518" y="2104" width="498" height="684" frameX="-3" frameY="-7" frameWidth="509" frameHeight="693"/>
	<SubTexture name="fileNailFull0085" x="1026" y="2104" width="498" height="684" frameX="-3" frameY="-7" frameWidth="509" frameHeight="693"/>
	<SubTexture name="fileNailFull0086" x="1026" y="2104" width="498" height="684" frameX="-3" frameY="-7" frameWidth="509" frameHeight="693"/>
	<SubTexture name="fileNailFull0087" x="1534" y="2104" width="498" height="684" frameX="-3" frameY="-7" frameWidth="509" frameHeight="693"/>
	<SubTexture name="fileNailFull0088" x="1534" y="2104" width="498" height="684" frameX="-3" frameY="-7" frameWidth="509" frameHeight="693"/>
	<SubTexture name="fileNailFull0089" x="2042" y="2104" width="498" height="684" frameX="-3" frameY="-7" frameWidth="509" frameHeight="693"/>
	<SubTexture name="fileNailFull0090" x="2042" y="2104" width="498" height="684" frameX="-3" frameY="-7" frameWidth="509" frameHeight="693"/>
	<SubTexture name="fileNailFull0091" x="2550" y="2104" width="495" height="684" frameX="-3" frameY="-7" frameWidth="509" frameHeight="693"/>
	<SubTexture name="fileNailFull0092" x="2550" y="2104" width="495" height="684" frameX="-3" frameY="-7" frameWidth="509" frameHeight="693"/>
	<SubTexture name="fileNailFull0093" x="3055" y="2104" width="492" height="680" frameX="-3" frameY="-11" frameWidth="509" frameHeight="693"/>
	<SubTexture name="fileNailFull0094" x="3055" y="2104" width="492" height="680" frameX="-3" frameY="-11" frameWidth="509" frameHeight="693"/>
	<SubTexture name="fileNailFull0095" x="3557" y="2104" width="492" height="676" frameX="-3" frameY="-15" frameWidth="509" frameHeight="693"/>
	<SubTexture name="fileNailFull0096" x="3557" y="2104" width="492" height="676" frameX="-3" frameY="-15" frameWidth="509" frameHeight="693"/>
	<SubTexture name="fileNailFull0097" x="4059" y="2104" width="492" height="675" frameX="-3" frameY="-16" frameWidth="509" frameHeight="693"/>
	<SubTexture name="fileNailFull0098" x="4561" y="2104" width="492" height="675" frameX="-3" frameY="-16" frameWidth="509" frameHeight="693"/>
	<SubTexture name="fileNailFull0099" x="5063" y="2104" width="494" height="680" frameX="-3" frameY="-11" frameWidth="509" frameHeight="693"/>
	<SubTexture name="fileNailFull0100" x="5567" y="2104" width="494" height="680" frameX="-3" frameY="-11" frameWidth="509" frameHeight="693"/>
	<SubTexture name="fileNailFull0101" x="6071" y="2104" width="496" height="684" frameX="-3" frameY="-7" frameWidth="509" frameHeight="693"/>
	<SubTexture name="fileNailFull0102" x="6071" y="2104" width="496" height="684" frameX="-3" frameY="-7" frameWidth="509" frameHeight="693"/>
	<SubTexture name="fileNailFull0103" x="6577" y="2104" width="498" height="684" frameX="-3" frameY="-7" frameWidth="509" frameHeight="693"/>
	<SubTexture name="fileNailFull0104" x="6577" y="2104" width="498" height="684" frameX="-3" frameY="-7" frameWidth="509" frameHeight="693"/>
	<SubTexture name="fileNailFull0105" x="6577" y="2104" width="498" height="684" frameX="-3" frameY="-7" frameWidth="509" frameHeight="693"/>
	<SubTexture name="fileNailFull0106" x="7085" y="2104" width="498" height="684" frameX="-3" frameY="-7" frameWidth="509" frameHeight="693"/>
	<SubTexture name="fileNailFull0107" x="7085" y="2104" width="498" height="684" frameX="-3" frameY="-7" frameWidth="509" frameHeight="693"/>
	<SubTexture name="fileNailFull0108" x="7593" y="2104" width="498" height="684" frameX="-3" frameY="-7" frameWidth="509" frameHeight="693"/>
	<SubTexture name="fileNailFull0109" x="7593" y="2104" width="498" height="684" frameX="-3" frameY="-7" frameWidth="509" frameHeight="693"/>
	<SubTexture name="fileNailFull0110" x="10" y="2798" width="496" height="682" frameX="-3" frameY="-9" frameWidth="509" frameHeight="693"/>
	<SubTexture name="fileNailFull0111" x="10" y="2798" width="496" height="682" frameX="-3" frameY="-9" frameWidth="509" frameHeight="693"/>
	<SubTexture name="fileNailFull0112" x="516" y="2798" width="493" height="682" frameX="-3" frameY="-9" frameWidth="509" frameHeight="693"/>
	<SubTexture name="fileNailFull0113" x="516" y="2798" width="493" height="682" frameX="-3" frameY="-9" frameWidth="509" frameHeight="693"/>
	<SubTexture name="fileNailFull0114" x="516" y="2798" width="493" height="682" frameX="-3" frameY="-9" frameWidth="509" frameHeight="693"/>
	<SubTexture name="fileNailFull0115" x="1019" y="2798" width="492" height="680" frameX="-3" frameY="-11" frameWidth="509" frameHeight="693"/>
	<SubTexture name="fileNailFull0116" x="1521" y="2798" width="499" height="682" frameX="0" frameY="-11" frameWidth="509" frameHeight="693"/>
	<SubTexture name="fileNailFull0117" x="2030" y="2798" width="499" height="681" frameX="0" frameY="-12" frameWidth="509" frameHeight="693"/>
	<SubTexture name="fileNailFull0118" x="2539" y="2798" width="494" height="680" frameX="-2" frameY="-12" frameWidth="509" frameHeight="693"/>
	<SubTexture name="fileNailFull0119" x="3043" y="2798" width="492" height="681" frameX="-3" frameY="-10" frameWidth="509" frameHeight="693"/>
	<SubTexture name="fileNailFull0120" x="3043" y="2798" width="492" height="681" frameX="-3" frameY="-10" frameWidth="509" frameHeight="693"/>
	<SubTexture name="fileNailFull0121" x="3545" y="2798" width="492" height="686" frameX="-3" frameY="-5" frameWidth="509" frameHeight="693"/>
	<SubTexture name="fileNailFull0122" x="4047" y="2798" width="492" height="687" frameX="-3" frameY="-4" frameWidth="509" frameHeight="693"/>
	<SubTexture name="fileNailFull0123" x="4549" y="2798" width="492" height="687" frameX="-3" frameY="-4" frameWidth="509" frameHeight="693"/>
	<SubTexture name="fileNailFull0124" x="4549" y="2798" width="492" height="687" frameX="-3" frameY="-4" frameWidth="509" frameHeight="693"/>
	<SubTexture name="fileNailFull0125" x="5051" y="2798" width="492" height="687" frameX="-3" frameY="-4" frameWidth="509" frameHeight="693"/>
	<SubTexture name="fileNailFull0126" x="5051" y="2798" width="492" height="687" frameX="-3" frameY="-4" frameWidth="509" frameHeight="693"/>
	<SubTexture name="fileNailFull0127" x="5051" y="2798" width="492" height="687" frameX="-3" frameY="-4" frameWidth="509" frameHeight="693"/>
	<SubTexture name="fileNailFull0128" x="5553" y="2798" width="492" height="688" frameX="-3" frameY="-3" frameWidth="509" frameHeight="693"/>
	<SubTexture name="fileNailFull0129" x="5553" y="2798" width="492" height="688" frameX="-3" frameY="-3" frameWidth="509" frameHeight="693"/>
	<SubTexture name="fileNailFull0130" x="6055" y="2798" width="492" height="687" frameX="-3" frameY="-4" frameWidth="509" frameHeight="693"/>
	<SubTexture name="fileNailFull0131" x="6557" y="2798" width="499" height="689" frameX="0" frameY="-4" frameWidth="509" frameHeight="693"/>
	<SubTexture name="fileNailFull0132" x="7066" y="2798" width="499" height="686" frameX="0" frameY="-7" frameWidth="509" frameHeight="693"/>
	<SubTexture name="fileNailFull0133" x="7575" y="2798" width="494" height="685" frameX="-2" frameY="-7" frameWidth="509" frameHeight="693"/>
	<SubTexture name="fileNailFull0134" x="10" y="3497" width="492" height="682" frameX="-3" frameY="-9" frameWidth="509" frameHeight="693"/>
	<SubTexture name="fileNailFull0135" x="512" y="3497" width="492" height="682" frameX="-3" frameY="-9" frameWidth="509" frameHeight="693"/>
	<SubTexture name="fileNailFull0136" x="1014" y="3497" width="492" height="682" frameX="-3" frameY="-9" frameWidth="509" frameHeight="693"/>
	<SubTexture name="fileNailFull0137" x="1516" y="3497" width="492" height="685" frameX="-3" frameY="-6" frameWidth="509" frameHeight="693"/>
	<SubTexture name="fileNailFull0138" x="2018" y="3497" width="492" height="685" frameX="-3" frameY="-6" frameWidth="509" frameHeight="693"/>
	<SubTexture name="fileNailFull0139" x="2520" y="3497" width="492" height="685" frameX="-3" frameY="-6" frameWidth="509" frameHeight="693"/>
	<SubTexture name="fileNailFull0140" x="3022" y="3497" width="492" height="685" frameX="-3" frameY="-6" frameWidth="509" frameHeight="693"/>
	<SubTexture name="fileNailFull0141" x="3022" y="3497" width="492" height="685" frameX="-3" frameY="-6" frameWidth="509" frameHeight="693"/>
	<SubTexture name="fileNailFull0142" x="3022" y="3497" width="492" height="685" frameX="-3" frameY="-6" frameWidth="509" frameHeight="693"/>
	<SubTexture name="fileNailFull0143" x="3524" y="3497" width="497" height="685" frameX="-3" frameY="-6" frameWidth="509" frameHeight="693"/>
	<SubTexture name="fileNailFull0144" x="3524" y="3497" width="497" height="685" frameX="-3" frameY="-6" frameWidth="509" frameHeight="693"/>
	<SubTexture name="left0000" x="4031" y="3497" width="490" height="672" frameX="-3" frameY="0" frameWidth="497" frameHeight="674"/>
	<SubTexture name="left0001" x="4531" y="3497" width="497" height="674"/>
	<SubTexture name="left0002" x="5038" y="3497" width="497" height="674"/>
	<SubTexture name="left0003" x="5545" y="3497" width="492" height="673" frameX="-2" frameY="0" frameWidth="497" frameHeight="674"/>
	<SubTexture name="left0004" x="6047" y="3497" width="490" height="672" frameX="-3" frameY="0" frameWidth="497" frameHeight="674"/>
	<SubTexture name="left0005" x="6047" y="3497" width="490" height="672" frameX="-3" frameY="0" frameWidth="497" frameHeight="674"/>
	<SubTexture name="left0006" x="6547" y="3497" width="490" height="672" frameX="-3" frameY="0" frameWidth="497" frameHeight="674"/>
	<SubTexture name="left0007" x="6547" y="3497" width="490" height="672" frameX="-3" frameY="0" frameWidth="497" frameHeight="674"/>
	<SubTexture name="left0008" x="6547" y="3497" width="490" height="672" frameX="-3" frameY="0" frameWidth="497" frameHeight="674"/>
	<SubTexture name="left0009" x="6547" y="3497" width="490" height="672" frameX="-3" frameY="0" frameWidth="497" frameHeight="674"/>
	<SubTexture name="left0010" x="6547" y="3497" width="490" height="672" frameX="-3" frameY="0" frameWidth="497" frameHeight="674"/>
	<SubTexture name="left0011" x="6547" y="3497" width="490" height="672" frameX="-3" frameY="0" frameWidth="497" frameHeight="674"/>
	<SubTexture name="left0012" x="6547" y="3497" width="490" height="672" frameX="-3" frameY="0" frameWidth="497" frameHeight="674"/>
	<SubTexture name="left0013" x="6547" y="3497" width="490" height="672" frameX="-3" frameY="0" frameWidth="497" frameHeight="674"/>
	<SubTexture name="left0014" x="6547" y="3497" width="490" height="672" frameX="-3" frameY="0" frameWidth="497" frameHeight="674"/>
	<SubTexture name="right0000" x="7047" y="3497" width="511" height="688" frameX="-3" frameY="0" frameWidth="514" frameHeight="691"/>
	<SubTexture name="right0001" x="7568" y="3497" width="509" height="691" frameX="0" frameY="0" frameWidth="514" frameHeight="691"/>
	<SubTexture name="right0002" x="10" y="4198" width="507" height="691" frameX="0" frameY="0" frameWidth="514" frameHeight="691"/>
	<SubTexture name="right0003" x="527" y="4198" width="505" height="689" frameX="-2" frameY="0" frameWidth="514" frameHeight="691"/>
	<SubTexture name="right0004" x="1042" y="4198" width="508" height="688" frameX="-3" frameY="0" frameWidth="514" frameHeight="691"/>
	<SubTexture name="right0005" x="1042" y="4198" width="508" height="688" frameX="-3" frameY="0" frameWidth="514" frameHeight="691"/>
	<SubTexture name="right0006" x="1560" y="4198" width="505" height="688" frameX="-3" frameY="0" frameWidth="514" frameHeight="691"/>
	<SubTexture name="right0007" x="1560" y="4198" width="505" height="688" frameX="-3" frameY="0" frameWidth="514" frameHeight="691"/>
	<SubTexture name="right0008" x="1560" y="4198" width="505" height="688" frameX="-3" frameY="0" frameWidth="514" frameHeight="691"/>
	<SubTexture name="right0009" x="1560" y="4198" width="505" height="688" frameX="-3" frameY="0" frameWidth="514" frameHeight="691"/>
	<SubTexture name="right0010" x="1560" y="4198" width="505" height="688" frameX="-3" frameY="0" frameWidth="514" frameHeight="691"/>
	<SubTexture name="right0011" x="1560" y="4198" width="505" height="688" frameX="-3" frameY="0" frameWidth="514" frameHeight="691"/>
	<SubTexture name="right0012" x="1560" y="4198" width="505" height="688" frameX="-3" frameY="0" frameWidth="514" frameHeight="691"/>
	<SubTexture name="right0013" x="1560" y="4198" width="505" height="688" frameX="-3" frameY="0" frameWidth="514" frameHeight="691"/>
	<SubTexture name="right0014" x="1560" y="4198" width="505" height="688" frameX="-3" frameY="0" frameWidth="514" frameHeight="691"/>
	<SubTexture name="up0000" x="2075" y="4198" width="490" height="698" frameX="-3" frameY="0" frameWidth="497" frameHeight="700"/>
	<SubTexture name="up0001" x="2575" y="4198" width="497" height="700"/>
	<SubTexture name="up0002" x="3082" y="4198" width="492" height="696" frameX="-2" frameY="-2" frameWidth="497" frameHeight="700"/>
	<SubTexture name="up0003" x="3584" y="4198" width="491" height="696" frameX="-3" frameY="-2" frameWidth="497" frameHeight="700"/>
	<SubTexture name="up0004" x="4085" y="4198" width="491" height="693" frameX="-3" frameY="-5" frameWidth="497" frameHeight="700"/>
	<SubTexture name="up0005" x="4085" y="4198" width="491" height="693" frameX="-3" frameY="-5" frameWidth="497" frameHeight="700"/>
	<SubTexture name="up0006" x="4586" y="4198" width="492" height="692" frameX="-3" frameY="-6" frameWidth="497" frameHeight="700"/>
	<SubTexture name="up0007" x="4586" y="4198" width="492" height="692" frameX="-3" frameY="-6" frameWidth="497" frameHeight="700"/>
	<SubTexture name="up0008" x="4586" y="4198" width="492" height="692" frameX="-3" frameY="-6" frameWidth="497" frameHeight="700"/>
	<SubTexture name="up0009" x="4586" y="4198" width="492" height="692" frameX="-3" frameY="-6" frameWidth="497" frameHeight="700"/>
	<SubTexture name="up0010" x="4586" y="4198" width="492" height="692" frameX="-3" frameY="-6" frameWidth="497" frameHeight="700"/>
	<SubTexture name="up0011" x="4586" y="4198" width="492" height="692" frameX="-3" frameY="-6" frameWidth="497" frameHeight="700"/>
	<SubTexture name="up0012" x="4586" y="4198" width="492" height="692" frameX="-3" frameY="-6" frameWidth="497" frameHeight="700"/>
	<SubTexture name="up0013" x="4586" y="4198" width="492" height="692" frameX="-3" frameY="-6" frameWidth="497" frameHeight="700"/>
	<SubTexture name="up0014" x="4586" y="4198" width="492" height="692" frameX="-3" frameY="-6" frameWidth="497" frameHeight="700"/>
</TextureAtlas>
